README.md
setup.py
exact_sinogram/__init__.py
exact_sinogram/radon_approx.py
exact_sinogram/radon_exact.py
exact_sinogram.egg-info/PKG-INFO
exact_sinogram.egg-info/SOURCES.txt
exact_sinogram.egg-info/dependency_links.txt
exact_sinogram.egg-info/not-zip-safe
exact_sinogram.egg-info/requires.txt
exact_sinogram.egg-info/top_level.txt