Metadata-Version: 1.0
Name: exact-sinogram
Version: 0.1.2
Summary: A Python package for the computation of the exact sinogram of different cathegories of phantoms for CT reconstruciton
Home-page: http://github.com/francescat93/Exact_sinogram
Author: Monica Dessole, Marta Gatto, Davide Poggiali, Francesca Tedeschi
Author-email: davide.poggiali@unipd.it
License: MIT
Platform: UNKNOWN
